<?xml version="1.0" encoding="UTF-8"?>
<gmd:MD_Metadata xmlns:gco="http://www.isotc211.org/2005/gco/" xmlns:gmd="http://www.isotc211.org/2005/gmd/" xmlns:gml="http://www.opengis.net/gml/3.2/" xmlns:gts="http://www.isotc211.org/2005/gts/" xmlns:srv="http://www.isotc211.org/2005/srv/" xmlns:xlink="http://www.w3.org/1999/xlink/" xmlns:xsi="http://www.w3.org/2001/XMLSchema-instance/">
	<gmd:fileIdentifier>
		<gco:CharacterString>GARISPANTAI250002022INDONESIA</gco:CharacterString>
	</gmd:fileIdentifier>
	<gmd:language>
		<gco:CharacterString>Bahasa Indonesia</gco:CharacterString>
	</gmd:language>
	<gmd:characterSet>
		<gmd:MD_CharacterSetCode codeList="./resources/codeList.xml#MD_CharacterSetCode" codeListValue="utf8">utf8</gmd:MD_CharacterSetCode>
	</gmd:characterSet>
	<gmd:parentIdentifier>
		<gco:CharacterString>-</gco:CharacterString>
	</gmd:parentIdentifier>
	<gmd:hierarchyLevel>
		<gmd:MD_ScopeCode codeList="./resources/codeList.xml#MD_ScopeCode" codeListValue="feature">feature</gmd:MD_ScopeCode>
	</gmd:hierarchyLevel>
	<gmd:hierarchyLevelName>
		<gco:CharacterString>GARISPANTAI_LN</gco:CharacterString>
	</gmd:hierarchyLevelName>
	<gmd:contact>
		<gmd:CI_ResponsibleParty>
			<gmd:individualName>
				<gco:CharacterString>Yosef Dwi Sigit Purnomo</gco:CharacterString>
			</gmd:individualName>
			<gmd:organisationName>
				<gco:CharacterString>Badan Informasi Geospasial</gco:CharacterString>
			</gmd:organisationName>
			<gmd:positionName>
				<gco:CharacterString>Kepala Pusat Pemetaan Kelautan dan Lingkungan Pantai</gco:CharacterString>
			</gmd:positionName>
			<gmd:role>
				<gmd:CI_RoleCode codeList="./resources/codeList.xml#CI_RoleCode" codeListValue="Produsen Data">Produsen Data</gmd:CI_RoleCode>
			</gmd:role>
		</gmd:CI_ResponsibleParty>
	</gmd:contact>
	<gmd:contact>
		<gmd:CI_ResponsibleParty>
			<gmd:individualName>
				<gco:CharacterString>Suprajaka</gco:CharacterString>
			</gmd:individualName>
			<gmd:organisationName>
				<gco:CharacterString>Badan Informasi Geospasial</gco:CharacterString>
			</gmd:organisationName>
			<gmd:positionName>
				<gco:CharacterString>Kepala Pusat Penelitian, Promosi dan Kerjasama</gco:CharacterString>
			</gmd:positionName>
			<gmd:contactInfo>
				<gmd:CI_Contact>
					<gmd:phone>
						<gmd:CI_Telephone>
							<gmd:voice>
								<gco:CharacterString>021-8753155, 87908988</gco:CharacterString>
							</gmd:voice>
						</gmd:CI_Telephone>
					</gmd:phone>
					<gmd:address>
						<gmd:CI_Address>
							<gmd:deliveryPoint>
								<gco:CharacterString>Jl. Raya Jakarta Bogor Km. 46 Cibinong</gco:CharacterString>
							</gmd:deliveryPoint>
							<gmd:city>
								<gco:CharacterString>Kabupaten Bogor</gco:CharacterString>
							</gmd:city>
							<gmd:administrativeArea>
								<gco:CharacterString>Jawa Barat</gco:CharacterString>
							</gmd:administrativeArea>
							<gmd:postalCode>
								<gco:CharacterString>16911</gco:CharacterString>
							</gmd:postalCode>
							<gmd:country>
								<gmd:Country codeList="http://www.iso.org/iso/country_codes/iso_3166_code_lists.htm" codeListValue="ID" codeSpace="ISO3166-1">ID</gmd:Country>
							</gmd:country>
							<gmd:electronicMailAddress>
								<gco:CharacterString>info@big.go.id</gco:CharacterString>
							</gmd:electronicMailAddress>
						</gmd:CI_Address>
					</gmd:address>
				</gmd:CI_Contact>
			</gmd:contactInfo>
			<gmd:role>
				<gmd:CI_RoleCode codeList="./resources/codeList.xml#CI_RoleCode" codeListValue="distributor">distributor</gmd:CI_RoleCode>
			</gmd:role>
		</gmd:CI_ResponsibleParty>
	</gmd:contact>
	<gmd:contact>
		<gmd:CI_ResponsibleParty>
			<gmd:individualName>
				<gco:CharacterString>Rachman Rifai, S.Si., M.Si, M.Sc</gco:CharacterString>
			</gmd:individualName>
			<gmd:organisationName>
				<gco:CharacterString>Pusat Pengelolaan dan Penyebarluasan Informasi Geospasial</gco:CharacterString>
			</gmd:organisationName>
			<gmd:positionName>
				<gco:CharacterString>Kepala Pusat Pengelolaan dan Penyebarluasan Informasi Geospasial</gco:CharacterString>
			</gmd:positionName>
			<gmd:contactInfo>
				<gmd:CI_Contact>
					<gmd:phone>
						<gmd:CI_Telephone>
							<gmd:voice>
								<gco:CharacterString>+62218753155</gco:CharacterString>
							</gmd:voice>
							<gmd:facsimile>
								<gco:CharacterString>+62218753155</gco:CharacterString>
							</gmd:facsimile>
						</gmd:CI_Telephone>
					</gmd:phone>
					<gmd:address>
						<gmd:CI_Address>
							<gmd:deliveryPoint>
								<gco:CharacterString>Jl. Raya Jakarta - Bogor KM. 46 Cibinong</gco:CharacterString>
							</gmd:deliveryPoint>
							<gmd:city>
								<gco:CharacterString>Kabupaten Bogor</gco:CharacterString>
							</gmd:city>
							<gmd:administrativeArea>
								<gco:CharacterString>Jawa Barat</gco:CharacterString>
							</gmd:administrativeArea>
							<gmd:postalCode>
								<gco:CharacterString>16911</gco:CharacterString>
							</gmd:postalCode>
							<gmd:country>
								<gmd:Country codeList="http://www.iso.org/iso/country_codes/iso_3166_code_lists.htm" codeListValue="ID" codeSpace="ISO3166-1">ID</gmd:Country>
							</gmd:country>
							<gmd:electronicMailAddress>
								<gco:CharacterString>info@big.go.id</gco:CharacterString>
							</gmd:electronicMailAddress>
						</gmd:CI_Address>
					</gmd:address>
					<gmd:hoursOfService>
						<gco:CharacterString>07.30-16.00 WIB</gco:CharacterString>
					</gmd:hoursOfService>
					<gmd:contactInstructions>
						<gco:CharacterString>Senin-Jumat</gco:CharacterString>
					</gmd:contactInstructions>
				</gmd:CI_Contact>
			</gmd:contactInfo>
			<gmd:role>
				<gmd:CI_RoleCode codeList="./resources/codeList.xml#CI_RoleCode" codeListValue="Walidata">Walidata</gmd:CI_RoleCode>
			</gmd:role>
		</gmd:CI_ResponsibleParty>
	</gmd:contact>
	<gmd:dateStamp>
		<gco:Date>2022-08-26</gco:Date>
	</gmd:dateStamp>
	<gmd:metadataStandardName>
		<gco:CharacterString>ISO 19115 Geographic Information - Metadata, ISO 19139 Geographic Information - Metadata - Implementation Specification</gco:CharacterString>
	</gmd:metadataStandardName>
	<gmd:metadataStandardVersion>
		<gco:CharacterString>ISO 19139 - 2007</gco:CharacterString>
	</gmd:metadataStandardVersion>
	<gmd:dataSetURI>
		<gco:CharacterString>https://geoservices.big.go.id/rbi/rest/services/GARISPANTAI/GarisPantai_25K/MapServer</gco:CharacterString>
	</gmd:dataSetURI>
	<gmd:spatialRepresentationInfo>
		<gmd:MD_VectorSpatialRepresentation>
			<gmd:topologyLevel>
				<gmd:MD_TopologyLevelCode codeList="./resources/codeList.xml#MD_TopologyLevelCode" codeListValue="geometryOnly">geometryOnly</gmd:MD_TopologyLevelCode>
			</gmd:topologyLevel>
			<gmd:geometricObjects>
				<gmd:MD_GeometricObjects>
					<gmd:geometricObjectType>
						<gmd:MD_GeometricObjectTypeCode codeList="./resources/codeList.xml#MD_GeometricObjectTypeCode" codeListValue="curve">curve</gmd:MD_GeometricObjectTypeCode>
					</gmd:geometricObjectType>
					<gmd:geometricObjectCount>
						<gco:Integer>42075</gco:Integer>
					</gmd:geometricObjectCount>
				</gmd:MD_GeometricObjects>
			</gmd:geometricObjects>
		</gmd:MD_VectorSpatialRepresentation>
	</gmd:spatialRepresentationInfo>
	<gmd:referenceSystemInfo>
		<gmd:MD_ReferenceSystem>
			<gmd:referenceSystemIdentifier>
				<gmd:RS_Identifier>
					<gmd:code>
						<gco:CharacterString>4326</gco:CharacterString>
					</gmd:code>
					<gmd:codeSpace>
						<gco:CharacterString>EPSG</gco:CharacterString>
					</gmd:codeSpace>
					<gmd:version>
						<gco:CharacterString>6.14(3.0.1)</gco:CharacterString>
					</gmd:version>
				</gmd:RS_Identifier>
			</gmd:referenceSystemIdentifier>
		</gmd:MD_ReferenceSystem>
	</gmd:referenceSystemInfo>
	<gmd:identificationInfo>
		<gmd:MD_DataIdentification>
			<gmd:citation>
				<gmd:CI_Citation>
					<gmd:title>
						<gco:CharacterString>Garis Pantai Indonesia Skala 1:25000 Tahun 2022</gco:CharacterString>
					</gmd:title>
					<gmd:alternateTitle>
						<gco:CharacterString>Garis Pantai Indonesia 25K 2022</gco:CharacterString>
					</gmd:alternateTitle>
					<gmd:date>
						<gmd:CI_Date>
							<gmd:date>
								<gco:Date>2022-07-25</gco:Date>
							</gmd:date>
							<gmd:dateType>
								<gmd:CI_DateTypeCode codeList="./resources/codeList.xml#CI_DateTypeCode" codeListValue="creation">creation</gmd:CI_DateTypeCode>
							</gmd:dateType>
						</gmd:CI_Date>
					</gmd:date>
					<gmd:date>
						<gmd:CI_Date>
							<gmd:date>
								<gco:Date>2022-07-25</gco:Date>
							</gmd:date>
							<gmd:dateType>
								<gmd:CI_DateTypeCode codeList="./resources/codeList.xml#CI_DateTypeCode" codeListValue="publication">publication</gmd:CI_DateTypeCode>
							</gmd:dateType>
						</gmd:CI_Date>
					</gmd:date>
					<gmd:editionDate>
						<gco:Date>2022-07-25</gco:Date>
					</gmd:editionDate>
					<gmd:citedResponsibleParty>
						<gmd:CI_ResponsibleParty>
							<gmd:individualName>
								<gco:CharacterString>Yosef Dwi Sigit Purnomo</gco:CharacterString>
							</gmd:individualName>
							<gmd:organisationName>
								<gco:CharacterString>Badan Informasi Geospasial</gco:CharacterString>
							</gmd:organisationName>
							<gmd:positionName>
								<gco:CharacterString>Kepala Pusat Pemetaan Kelautan dan Lingkungan Pantai</gco:CharacterString>
							</gmd:positionName>
							<gmd:role>
								<gmd:CI_RoleCode codeList="http://www.isotc211.org/2005/resources/Codelist/gmxCodelists.xml#CI_RoleCode" codeListValue="originator" codeSpace="ISOTC211/19115">originator</gmd:CI_RoleCode>
							</gmd:role>
						</gmd:CI_ResponsibleParty>
					</gmd:citedResponsibleParty>
					<gmd:citedResponsibleParty>
						<gmd:CI_ResponsibleParty>
							<gmd:individualName>
								<gco:CharacterString>Rachman Rifai, S.Si., M.Si, M.Sc</gco:CharacterString>
							</gmd:individualName>
							<gmd:organisationName>
								<gco:CharacterString>Pusat Pengelolaan dan Penyebarluasan Informasi Geospasial</gco:CharacterString>
							</gmd:organisationName>
							<gmd:positionName>
								<gco:CharacterString>Kepala Pusat Pengelolaan dan Penyebarluasan Informasi Geospasial</gco:CharacterString>
							</gmd:positionName>
							<gmd:contactInfo>
								<gmd:CI_Contact>
									<gmd:phone>
										<gmd:CI_Telephone>
											<gmd:voice>
												<gco:CharacterString>+62218753155</gco:CharacterString>
											</gmd:voice>
											<gmd:facsimile>
												<gco:CharacterString>+62218753155</gco:CharacterString>
											</gmd:facsimile>
										</gmd:CI_Telephone>
									</gmd:phone>
									<gmd:address>
										<gmd:CI_Address>
											<gmd:deliveryPoint>
												<gco:CharacterString>Jl. Raya Jakarta - Bogor KM. 46 Cibinong</gco:CharacterString>
											</gmd:deliveryPoint>
											<gmd:city>
												<gco:CharacterString>Kabupaten Bogor</gco:CharacterString>
											</gmd:city>
											<gmd:administrativeArea>
												<gco:CharacterString>Jawa Barat</gco:CharacterString>
											</gmd:administrativeArea>
											<gmd:postalCode>
												<gco:CharacterString>16911</gco:CharacterString>
											</gmd:postalCode>
											<gmd:country>
												<gmd:Country codeList="http://www.iso.org/iso/country_codes/iso_3166_code_lists.htm" codeListValue="ID" codeSpace="ISO3166-1">ID</gmd:Country>
											</gmd:country>
											<gmd:electronicMailAddress>
												<gco:CharacterString>info@big.go.id</gco:CharacterString>
											</gmd:electronicMailAddress>
										</gmd:CI_Address>
									</gmd:address>
									<gmd:hoursOfService>
										<gco:CharacterString>07.30-16.00 WIB</gco:CharacterString>
									</gmd:hoursOfService>
									<gmd:contactInstructions>
										<gco:CharacterString>Senin-Jumat</gco:CharacterString>
									</gmd:contactInstructions>
								</gmd:CI_Contact>
							</gmd:contactInfo>
							<gmd:role>
								<gmd:CI_RoleCode codeList="http://www.isotc211.org/2005/resources/Codelist/gmxCodelists.xml#CI_RoleCode" codeListValue="custodian" codeSpace="ISOTC211/19115">custodian</gmd:CI_RoleCode>
							</gmd:role>
						</gmd:CI_ResponsibleParty>
					</gmd:citedResponsibleParty>
					<gmd:presentationForm>
						<gmd:CI_PresentationFormCode codeList="./resources/codeList.xml#CI_PresentationFormCode" codeListValue="mapDigital">mapDigital</gmd:CI_PresentationFormCode>
					</gmd:presentationForm>
				</gmd:CI_Citation>
			</gmd:citation>
			<gmd:abstract>
				<gco:CharacterString>Garis Pantai adalah garis pertemuan antara daratan dan lautan yang dipengaruhi pasang surut air laut.Data garis pantai ini merupakan data pemutakhiran tahun 2022, berdasarkan data penetapan Garis Pantai 2021 yang telah dipetakan oleh Pusat PKLP. Data ini merupakan data garis pantai pasang tertinggi (definitif) dan sebagian bersifat indikatif, dimana akan dapat ditetapkan sebagai pasang tertinggi definitif dalam Mean High Water Spring (MHWS) setelah terdapat hasil survei detil di area pantai tersebut.Garis pantai indikatif adalah garis yang mengindikasikan batas darat dan laut yang diperoleh dari delineasi data sekunder seperti citra satelit, foto udara, dll Untuk tahun 2022, PPKLP melakukan pengumpulan data-data survei, serta data hasil konsultasi teknis garis pantai dengan K/L/Pemda untuk melakukan pemutakhiran Garis Pantai Penetapan BIG tahun 2021 yang bersumber dari Data Survei Hidrografi (2015-2020, dengan metode hidrografi, shoreline transect, survei lidar batimetri), Data Hasil Konsultasi Teknis Garis Pantai (2016 - Maret 2022, sebagian besar dengan metode delinieasi citra satelit dan foto udara) dan Data Digitasi Foto Udara UAV area sekitar Titik Dasar (2011-2014, dengan metode delineasi foto udara UAV). Data garis pantai yang dimutakhirkan mencakup data garis pantai hasil survei (pasang tertinggi, surut terendah, muka laut rata-rata dan garis pantai indikatif.</gco:CharacterString>
			</gmd:abstract>
			<gmd:purpose>
				<gco:CharacterString>Data ini merupakan garis pantai tertinggi, dimana sebagian bersifat indikatif dan sebagian lain definitif. Data ini dapat digunakan sesuai dengan kebutuhan dan kepentingan pengguna.</gco:CharacterString>
			</gmd:purpose>
			<gmd:credit>
				<gco:CharacterString>Pusat Pemetaan Kelautan dan Lingkungan Pantai - Badan Informasi Geospasial</gco:CharacterString>
			</gmd:credit>
			<gmd:status>
				<gmd:MD_ProgressCode codeList="./resources/codeList.xml#MD_ProgressCode" codeListValue="completed">completed</gmd:MD_ProgressCode>
			</gmd:status>
			<gmd:pointOfContact>
				<gmd:CI_ResponsibleParty>
					<gmd:individualName>
						<gco:CharacterString>Yosef Dwi Sigit Purnomo</gco:CharacterString>
					</gmd:individualName>
					<gmd:organisationName>
						<gco:CharacterString>Badan Informasi Geospasial</gco:CharacterString>
					</gmd:organisationName>
					<gmd:positionName>
						<gco:CharacterString>Kepala Pusat Pemetaan Kelautan dan Lingkungan Pantai</gco:CharacterString>
					</gmd:positionName>
					<gmd:role>
						<gmd:CI_RoleCode codeList="./resources/codeList.xml#CI_RoleCode" codeListValue="Produsen Data">Produsen Data</gmd:CI_RoleCode>
					</gmd:role>
				</gmd:CI_ResponsibleParty>
			</gmd:pointOfContact>
			<gmd:pointOfContact>
				<gmd:CI_ResponsibleParty>
					<gmd:individualName>
						<gco:CharacterString>Suprajaka</gco:CharacterString>
					</gmd:individualName>
					<gmd:organisationName>
						<gco:CharacterString>Badan Informasi Geospasial</gco:CharacterString>
					</gmd:organisationName>
					<gmd:positionName>
						<gco:CharacterString>Kepala Pusat Penelitian, Promosi dan Kerjasama</gco:CharacterString>
					</gmd:positionName>
					<gmd:contactInfo>
						<gmd:CI_Contact>
							<gmd:phone>
								<gmd:CI_Telephone>
									<gmd:voice>
										<gco:CharacterString>021-8753155, 87908988</gco:CharacterString>
									</gmd:voice>
								</gmd:CI_Telephone>
							</gmd:phone>
							<gmd:address>
								<gmd:CI_Address>
									<gmd:deliveryPoint>
										<gco:CharacterString>Jl. Raya Jakarta Bogor Km. 46 Cibinong</gco:CharacterString>
									</gmd:deliveryPoint>
									<gmd:city>
										<gco:CharacterString>Kabupaten Bogor</gco:CharacterString>
									</gmd:city>
									<gmd:administrativeArea>
										<gco:CharacterString>Jawa Barat</gco:CharacterString>
									</gmd:administrativeArea>
									<gmd:postalCode>
										<gco:CharacterString>16911</gco:CharacterString>
									</gmd:postalCode>
									<gmd:country>
										<gco:CharacterString>Indonesia</gco:CharacterString>
									</gmd:country>
									<gmd:electronicMailAddress>
										<gco:CharacterString>info@big.go.id</gco:CharacterString>
									</gmd:electronicMailAddress>
								</gmd:CI_Address>
							</gmd:address>
						</gmd:CI_Contact>
					</gmd:contactInfo>
					<gmd:role>
						<gmd:CI_RoleCode codeList="./resources/codeList.xml#CI_RoleCode" codeListValue="distributor">distributor</gmd:CI_RoleCode>
					</gmd:role>
				</gmd:CI_ResponsibleParty>
			</gmd:pointOfContact>
			<gmd:pointOfContact>
				<gmd:CI_ResponsibleParty>
					<gmd:individualName>
						<gco:CharacterString>Rachman Rifai, S.Si., M.Si, M.Sc</gco:CharacterString>
					</gmd:individualName>
					<gmd:organisationName>
						<gco:CharacterString>Pusat Pengelolaan dan Penyebarluasan Informasi Geospasial</gco:CharacterString>
					</gmd:organisationName>
					<gmd:positionName>
						<gco:CharacterString>Kepala Pusat Pengelolaan dan Penyebarluasan Informasi Geospasial</gco:CharacterString>
					</gmd:positionName>
					<gmd:contactInfo>
						<gmd:CI_Contact>
							<gmd:phone>
								<gmd:CI_Telephone>
									<gmd:voice>
										<gco:CharacterString>+62218753155</gco:CharacterString>
									</gmd:voice>
									<gmd:facsimile>
										<gco:CharacterString>+62218753155</gco:CharacterString>
									</gmd:facsimile>
								</gmd:CI_Telephone>
							</gmd:phone>
							<gmd:address>
								<gmd:CI_Address>
									<gmd:deliveryPoint>
										<gco:CharacterString>Jl. Raya Jakarta - Bogor KM. 46 Cibinong</gco:CharacterString>
									</gmd:deliveryPoint>
									<gmd:city>
										<gco:CharacterString>Kabupaten Bogor</gco:CharacterString>
									</gmd:city>
									<gmd:administrativeArea>
										<gco:CharacterString>Jawa Barat</gco:CharacterString>
									</gmd:administrativeArea>
									<gmd:postalCode>
										<gco:CharacterString>16911</gco:CharacterString>
									</gmd:postalCode>
									<gmd:country>
										<gco:CharacterString>Indonesia</gco:CharacterString>
									</gmd:country>
									<gmd:electronicMailAddress>
										<gco:CharacterString>info@big.go.id</gco:CharacterString>
									</gmd:electronicMailAddress>
								</gmd:CI_Address>
							</gmd:address>
							<gmd:hoursOfService>
								<gco:CharacterString>07.30-16.00 WIB</gco:CharacterString>
							</gmd:hoursOfService>
							<gmd:contactInstructions>
								<gco:CharacterString>Senin-Jumat</gco:CharacterString>
							</gmd:contactInstructions>
						</gmd:CI_Contact>
					</gmd:contactInfo>
					<gmd:role>
						<gmd:CI_RoleCode codeList="./resources/codeList.xml#CI_RoleCode" codeListValue="Walidata">Walidata</gmd:CI_RoleCode>
					</gmd:role>
				</gmd:CI_ResponsibleParty>
			</gmd:pointOfContact>
			<gmd:resourceMaintenance>
				<gmd:MD_MaintenanceInformation>
					<gmd:maintenanceAndUpdateFrequency>
						<gmd:MD_MaintenanceFrequencyCode codeList="./resources/codeList.xml#MD_MaintenanceFrequencyCode" codeListValue="asNeeded">asNeeded</gmd:MD_MaintenanceFrequencyCode>
					</gmd:maintenanceAndUpdateFrequency>
					<gmd:userDefinedMaintenanceFrequency>
						<gts:TM_PeriodDuration>Yearly</gts:TM_PeriodDuration>
					</gmd:userDefinedMaintenanceFrequency>
				</gmd:MD_MaintenanceInformation>
			</gmd:resourceMaintenance>
			<gmd:resourceFormat>
				<gmd:MD_Format>
					<gmd:name>
						<gco:CharacterString>GDB</gco:CharacterString>
					</gmd:name>
					<gmd:version gco:nilReason="missing"/>
				</gmd:MD_Format>
			</gmd:resourceFormat>
			<gmd:descriptiveKeywords>
				<gmd:MD_Keywords>
					<gmd:keyword>
						<gco:CharacterString>2022</gco:CharacterString>
					</gmd:keyword>
					<gmd:type>
						<gmd:MD_KeywordTypeCode codeList="./resources/codeList.xml#MD_KeywordTypeCode" codeListValue="temporal">temporal</gmd:MD_KeywordTypeCode>
					</gmd:type>
				</gmd:MD_Keywords>
			</gmd:descriptiveKeywords>
			<gmd:descriptiveKeywords>
				<gmd:MD_Keywords>
					<gmd:keyword>
						<gco:CharacterString>Garis Pantai</gco:CharacterString>
					</gmd:keyword>
					<gmd:type>
						<gmd:MD_KeywordTypeCode codeList="./resources/codeList.xml#MD_KeywordTypeCode" codeListValue="theme">theme</gmd:MD_KeywordTypeCode>
					</gmd:type>
				</gmd:MD_Keywords>
			</gmd:descriptiveKeywords>
			<gmd:descriptiveKeywords>
				<gmd:MD_Keywords>
					<gmd:keyword>
						<gco:CharacterString>Indonesia</gco:CharacterString>
					</gmd:keyword>
				</gmd:MD_Keywords>
			</gmd:descriptiveKeywords>
			<gmd:descriptiveKeywords>
				<gmd:MD_Keywords>
					<gmd:keyword>
						<gco:CharacterString>Downloadable Data</gco:CharacterString>
					</gmd:keyword>
					<gmd:thesaurusName uuidref="723f6998-058e-11dc-8314-0800200c9a66"/>
				</gmd:MD_Keywords>
			</gmd:descriptiveKeywords>
			<gmd:resourceConstraints>
				<gmd:MD_Constraints>
					<gmd:useLimitation>
						<gco:CharacterString>Tidak digunakan untuk keperluan navigasi atau pelayaran</gco:CharacterString>
					</gmd:useLimitation>
				</gmd:MD_Constraints>
			</gmd:resourceConstraints>
			<gmd:spatialRepresentationType>
				<gmd:MD_SpatialRepresentationTypeCode codeList="./resources/codeList.xml#MD_SpatialRepresentationTypeCode" codeListValue="vector">vector</gmd:MD_SpatialRepresentationTypeCode>
			</gmd:spatialRepresentationType>
			<gmd:spatialResolution>
				<gmd:MD_Resolution>
					<gmd:distance>
						<gco:Distance uom="m">12.5</gco:Distance>
					</gmd:distance>
				</gmd:MD_Resolution>
			</gmd:spatialResolution>
			<gmd:spatialResolution>
				<gmd:MD_Resolution>
					<gmd:equivalentScale>
						<gmd:MD_RepresentativeFraction>
							<gmd:denominator>
								<gco:Integer>25000</gco:Integer>
							</gmd:denominator>
						</gmd:MD_RepresentativeFraction>
					</gmd:equivalentScale>
				</gmd:MD_Resolution>
			</gmd:spatialResolution>
			<gmd:language>
				<gco:CharacterString>Bahasa Indonesia</gco:CharacterString>
			</gmd:language>
			<gmd:characterSet>
				<gmd:MD_CharacterSetCode codeList="./resources/codeList.xml#MD_CharacterSetCode" codeListValue="utf8">utf8</gmd:MD_CharacterSetCode>
			</gmd:characterSet>
			<gmd:topicCategory>
				<gmd:MD_TopicCategoryCode>oceans</gmd:MD_TopicCategoryCode>
			</gmd:topicCategory>
			<gmd:topicCategory>
				<gmd:MD_TopicCategoryCode>inlandWaters</gmd:MD_TopicCategoryCode>
			</gmd:topicCategory>
			<gmd:topicCategory>
				<gmd:MD_TopicCategoryCode>elevation</gmd:MD_TopicCategoryCode>
			</gmd:topicCategory>
			<gmd:topicCategory>
				<gmd:MD_TopicCategoryCode>boundaries</gmd:MD_TopicCategoryCode>
			</gmd:topicCategory>
			<gmd:environmentDescription>
				<gco:CharacterString>Version 6.2 (Build 9200) ; Esri ArcGIS 10.6.1.9328</gco:CharacterString>
			</gmd:environmentDescription>
			<gmd:extent>
				<gmd:EX_Extent>
					<gmd:description>
						<gco:CharacterString>Seluruh Wilayah Negara Kesatuan Republik Indonesia</gco:CharacterString>
					</gmd:description>
					<gmd:geographicElement>
						<gmd:EX_GeographicBoundingBox>
							<gmd:extentTypeCode>
								<gco:Boolean>true</gco:Boolean>
							</gmd:extentTypeCode>
							<gmd:westBoundLongitude>
								<gco:Decimal>94.971911</gco:Decimal>
							</gmd:westBoundLongitude>
							<gmd:eastBoundLongitude>
								<gco:Decimal>141.019625</gco:Decimal>
							</gmd:eastBoundLongitude>
							<gmd:southBoundLatitude>
								<gco:Decimal>-11.007615</gco:Decimal>
							</gmd:southBoundLatitude>
							<gmd:northBoundLatitude>
								<gco:Decimal>6.076832</gco:Decimal>
							</gmd:northBoundLatitude>
						</gmd:EX_GeographicBoundingBox>
					</gmd:geographicElement>
					<gmd:geographicElement>
						<gmd:EX_GeographicDescription>
							<gmd:extentTypeCode>
								<gco:Boolean>false</gco:Boolean>
							</gmd:extentTypeCode>
							<gmd:geographicIdentifier gco:nilReason="missing"/>
						</gmd:EX_GeographicDescription>
					</gmd:geographicElement>
					<gmd:temporalElement gco:nilReason="missing"/>
					<gmd:verticalElement gco:nilReason="missing"/>
				</gmd:EX_Extent>
			</gmd:extent>
		</gmd:MD_DataIdentification>
	</gmd:identificationInfo>
	<gmd:distributionInfo>
		<gmd:MD_Distribution>
			<gmd:distributionFormat>
				<gmd:MD_Format>
					<gmd:name>
						<gco:CharacterString>GDB</gco:CharacterString>
					</gmd:name>
					<gmd:version>
						<gco:CharacterString>-</gco:CharacterString>
					</gmd:version>
				</gmd:MD_Format>
			</gmd:distributionFormat>
			<gmd:distributionFormat>
				<gmd:MD_Format>
					<gmd:name>
						<gco:CharacterString>File Geodatabase Feature Class</gco:CharacterString>
					</gmd:name>
					<gmd:version>
						<gco:CharacterString>-</gco:CharacterString>
					</gmd:version>
				</gmd:MD_Format>
			</gmd:distributionFormat>
			<gmd:distributor>
				<gmd:MD_Distributor>
					<gmd:distributorContact>
						<gmd:CI_ResponsibleParty>
							<gmd:individualName>
								<gco:CharacterString>Suprajaka</gco:CharacterString>
							</gmd:individualName>
							<gmd:organisationName>
								<gco:CharacterString>Badan Informasi Geospasial</gco:CharacterString>
							</gmd:organisationName>
							<gmd:positionName>
								<gco:CharacterString>Kepala Pusat Penelitian, Promosi dan Kerjasama</gco:CharacterString>
							</gmd:positionName>
							<gmd:contactInfo>
								<gmd:CI_Contact>
									<gmd:phone>
										<gmd:CI_Telephone>
											<gmd:voice>
												<gco:CharacterString>021-8753155, 87908988</gco:CharacterString>
											</gmd:voice>
										</gmd:CI_Telephone>
									</gmd:phone>
									<gmd:address>
										<gmd:CI_Address>
											<gmd:deliveryPoint>
												<gco:CharacterString>Jl. Raya Jakarta Bogor Km. 46 Cibinong</gco:CharacterString>
											</gmd:deliveryPoint>
											<gmd:city>
												<gco:CharacterString>Kabupaten Bogor</gco:CharacterString>
											</gmd:city>
											<gmd:administrativeArea>
												<gco:CharacterString>Jawa Barat</gco:CharacterString>
											</gmd:administrativeArea>
											<gmd:postalCode>
												<gco:CharacterString>16911</gco:CharacterString>
											</gmd:postalCode>
											<gmd:country>
												<gmd:Country codeList="http://www.iso.org/iso/country_codes/iso_3166_code_lists.htm" codeListValue="ID" codeSpace="ISO3166-1">ID</gmd:Country>
											</gmd:country>
											<gmd:electronicMailAddress>
												<gco:CharacterString>info@big.go.id</gco:CharacterString>
											</gmd:electronicMailAddress>
										</gmd:CI_Address>
									</gmd:address>
								</gmd:CI_Contact>
							</gmd:contactInfo>
							<gmd:role>
								<gmd:CI_RoleCode codeList="http://www.isotc211.org/2005/resources/Codelist/gmxCodelists.xml#CI_RoleCode" codeListValue="distributor" codeSpace="ISOTC211/19115">distributor</gmd:CI_RoleCode>
							</gmd:role>
						</gmd:CI_ResponsibleParty>
					</gmd:distributorContact>
				</gmd:MD_Distributor>
			</gmd:distributor>
			<gmd:transferOptions>
				<gmd:MD_DigitalTransferOptions>
					<gmd:unitsOfDistribution>
						<gco:CharacterString>MB</gco:CharacterString>
					</gmd:unitsOfDistribution>
					<gmd:transferSize>
						<gco:Real>57.5</gco:Real>
					</gmd:transferSize>
					<gmd:onLine>
						<gmd:CI_OnlineResource>
							<gmd:linkage>
								<gmd:URL>https://geoservices.big.go.id/rbi/rest/services/GARISPANTAI/GarisPantai_25K/MapServer</gmd:URL>
							</gmd:linkage>
							<gmd:protocol>
								<gco:CharacterString>ESRI:ArcGIS:MapServer</gco:CharacterString>
							</gmd:protocol>
							<gmd:name>
								<gco:CharacterString>Garis Pantai Indonesia Skala 1:25000 Tahun 2022</gco:CharacterString>
							</gmd:name>
							<gmd:description>
								<gco:CharacterString>Garis Pantai Indonesia Skala 1:25000 Tahun 2022</gco:CharacterString>
							</gmd:description>
						</gmd:CI_OnlineResource>
					</gmd:onLine>
				</gmd:MD_DigitalTransferOptions>
			</gmd:transferOptions>
		</gmd:MD_Distribution>
	</gmd:distributionInfo>
	<gmd:dataQualityInfo>
		<gmd:DQ_DataQuality>
			<gmd:scope>
				<gmd:DQ_Scope>
					<gmd:level>
						<gmd:MD_ScopeCode codeList="http://www.isotc211.org/2005/resources/Codelist/gmxCodelists.xml#MD_ScopeCode" codeListValue="feature" codeSpace="ISOTC211/19115">feature</gmd:MD_ScopeCode>
					</gmd:level>
				</gmd:DQ_Scope>
			</gmd:scope>
			<gmd:report>
				<gmd:DQ_TopologicalConsistency>
					<gmd:result>
						<gmd:DQ_ConformanceResult>
							<gmd:specification gco:nilReason="missing"/>
							<gmd:explanation gco:nilReason="missing"/>
							<gmd:pass>
								<gco:Boolean>true</gco:Boolean>
							</gmd:pass>
						</gmd:DQ_ConformanceResult>
					</gmd:result>
				</gmd:DQ_TopologicalConsistency>
			</gmd:report>
			<gmd:lineage>
				<gmd:LI_Lineage>
					<gmd:statement>
						<gco:CharacterString>Data ini dimutakhirkan dari Garis Pantai Penetapan BIG tahun 2021, dimana sumber data berupa: 1. Data Survei Hidrografi (2015-2020, dengan metode hidrografi, shoreline transect, survei lidar batimetri) 2. Data Hasil Konsultasi Teknis Garis Pantai (2016 - Maret 2022, dengan metode delinieasi citra satelit dan foto udara) 3. Data Digitasi Foto Udara UAV area sekitar Titik Dasar (2011-2014, dengan metode delineasi foto udara UAV).</gco:CharacterString>
					</gmd:statement>
				</gmd:LI_Lineage>
			</gmd:lineage>
		</gmd:DQ_DataQuality>
	</gmd:dataQualityInfo>
	<gmd:applicationSchemaInfo>
		<gmd:MD_ApplicationSchemaInformation>
			<gmd:name gco:nilReason="missing"/>
			<gmd:schemaLanguage>
				<gco:CharacterString>xml</gco:CharacterString>
			</gmd:schemaLanguage>
			<gmd:constraintLanguage gco:nilReason="missing"/>
		</gmd:MD_ApplicationSchemaInformation>
	</gmd:applicationSchemaInfo>
	<gmd:metadataMaintenance>
		<gmd:MD_MaintenanceInformation>
			<gmd:maintenanceAndUpdateFrequency>
				<gmd:MD_MaintenanceFrequencyCode codeList="./resources/codeList.xml#MD_MaintenanceFrequencyCode" codeListValue="asNeeded">asNeeded</gmd:MD_MaintenanceFrequencyCode>
			</gmd:maintenanceAndUpdateFrequency>
			<gmd:userDefinedMaintenanceFrequency>
				<gts:TM_PeriodDuration>metadata dimutakhirkan mengikuti update data garis pantai</gts:TM_PeriodDuration>
			</gmd:userDefinedMaintenanceFrequency>
			<gmd:updateScope>
				<gmd:MD_ScopeCode codeList="./resources/codeList.xml#MD_ScopeCode" codeListValue="feature">feature</gmd:MD_ScopeCode>
			</gmd:updateScope>
			<gmd:maintenanceNote>
				<gco:CharacterString>metadata dimutakhirkan mengikuti update data garis pantai</gco:CharacterString>
			</gmd:maintenanceNote>
		</gmd:MD_MaintenanceInformation>
	</gmd:metadataMaintenance>
	<Esri><CreaDate>20240724</CreaDate><CreaTime>09400400</CreaTime><ArcGISstyle>ISO 19139 Metadata Implementation Specification GML3.2</ArcGISstyle><SyncOnce>TRUE</SyncOnce><DataProperties><itemProps><itemLocation><linkage Sync="TRUE">file://\\LAPTOP-NDACA94K\C$\2024\DATA\20240723_CROPPING_KEPRI\KOTA BATAM\GARISPANTAI250002022INDONESIA</linkage><protocol Sync="TRUE">Local Area Network</protocol></itemLocation></itemProps><copyHistory><copy source="C:\2024\DATA\20240717_CROPPING_RIAU\KAB BENGKALIS\GARISPANTAI250002022INDONESIA" dest="\\LAPTOP-NDACA94K\C$\2024\DATA\20240723_CROPPING_KEPRI\KOTA BATAM\GARISPANTAI250002022INDONESIA" date="20240724" time="09400400"></copy></copyHistory></DataProperties></Esri></gmd:MD_Metadata>
<!--Metadata generated with CatMDEdit version 5.0-->
